fairy_slipper/__init__.py
fairy_slipper/app.py
fairy_slipper/app_routes.py
fairy_slipper/hooks.py
fairy_slipper/rest.py
fairy_slipper/version.py
fairy_slipper/cmd/__init__.py
fairy_slipper/cmd/docbkx_to_json.py
fairy_slipper/cmd/swagger_to_rst.py
fairy_slipper/cmd/tempest_log.py
fairy_slipper/cmd/wadl_to_swagger.py
fairy_slipper/cmd/wadl_to_swagger_valid.py
fairy_slipper/controllers/__init__.py
fairy_slipper/controllers/root.py
fairy_slipper/controllers/routes_inspector.py
fairy_slipper/templates/error.html
fairy_slipper/templates/index.html
fairy_slipper/templates/layout.html
fairy_slipper/tests/__init__.py
fairy_slipper/tests/base.py
fairy_slipper/tests/test_fairy_slipper.py
fairy_slipper/tests/test_functional.py
fairy_slipper/tests/test_rest.py
fairy_slipper/tests/test_units.py
fairy_slipper/tests/api_doc_fixture/index.json
fairy_slipper/tests/api_doc_fixture/identity/v2-tags.rst
fairy_slipper/tests/api_doc_fixture/identity/v2.rst
fairy_slipper/tests/cmd/__init__.py
fairy_slipper/tests/cmd/ch_test-link.xml
fairy_slipper/tests/cmd/ch_test-listitems.xml
fairy_slipper/tests/cmd/ch_test-table.xml
fairy_slipper/tests/cmd/ch_test-v1.xml
fairy_slipper/tests/cmd/ch_test-v3.xml
fairy_slipper/tests/cmd/test_docbkx_to_json.py
fairy_slipper/tests/cmd/test_tempest.py
fairy_slipper/tests/cmd/test_wadl_to_swagger.py
fairy_slipper/tests/cmd/test_wadl_to_swagger_valid.py
fairy_slipper/tests/mocha/test/validate_test.js
fairy_slipper-0.2.0.dist-info/DESCRIPTION.rst
fairy_slipper-0.2.0.dist-info/METADATA
fairy_slipper-0.2.0.dist-info/RECORD
fairy_slipper-0.2.0.dist-info/WHEEL
fairy_slipper-0.2.0.dist-info/entry_points.txt
fairy_slipper-0.2.0.dist-info/metadata.json
fairy_slipper-0.2.0.dist-info/pbr.json
fairy_slipper-0.2.0.dist-info/top_level.txt
