Metadata-Version: 2.0
Name: fairy-slipper
Version: 0.2.0
Summary: A project to make OpenStack API's self documententing.
Home-page: http://www.openstack.org/
Author: OpenStack
Author-email: russell.sim@gmail.com
License: UNKNOWN
Platform: UNKNOWN
Classifier: Environment :: OpenStack
Classifier: Intended Audience :: Information Technology
Classifier: Intended Audience :: System Administrators
Classifier: License :: OSI Approved :: Apache Software License
Classifier: Operating System :: POSIX :: Linux
Classifier: Programming Language :: Python
Classifier: Programming Language :: Python :: 2
Classifier: Programming Language :: Python :: 2.7
Classifier: Programming Language :: Python :: 2.6
Classifier: Programming Language :: Python :: 3
Classifier: Programming Language :: Python :: 3.3
Classifier: Programming Language :: Python :: 3.4
Requires-Dist: Babel (>=1.3)
Requires-Dist: docutils
Requires-Dist: jinja2
Requires-Dist: oslo.serialization
Requires-Dist: pbr (!=0.7,>=0.6,<2.0)
Requires-Dist: pecan
Requires-Dist: prettytable
Requires-Dist: webob
